superpoint_superglue_deployment/__init__.py
superpoint_superglue_deployment/__main__.py
superpoint_superglue_deployment/matcher.py
superpoint_superglue_deployment/superglue.py
superpoint_superglue_deployment/superglue_handler.py
superpoint_superglue_deployment/superpoint.py
superpoint_superglue_deployment/superpoint_handler.py
superpoint_superglue_deployment/version.py
superpoint_superglue_deployment/core/__init__.py
superpoint_superglue_deployment/core/utils.py
superpoint_superglue_deployment-0.0.3.dist-info/METADATA
superpoint_superglue_deployment-0.0.3.dist-info/WHEEL
superpoint_superglue_deployment-0.0.3.dist-info/entry_points.txt
superpoint_superglue_deployment-0.0.3.dist-info/top_level.txt
superpoint_superglue_deployment-0.0.3.dist-info/RECORD
