Metadata-Version: 2.1
Name: superpoint-superglue-deployment
Version: 0.0.3
Home-page: https://github.com/xmba15/superpoint_superglue_deployment
Author: Ba Tran
Classifier: Development Status :: 3 - Alpha
Classifier: Intended Audience :: Developers
Classifier: Programming Language :: Python :: 3
Classifier: Programming Language :: Python :: 3.6
Classifier: Programming Language :: Python :: 3.7
Classifier: Programming Language :: Python :: 3.8
Classifier: Programming Language :: Python :: 3.9
Requires-Dist: typing-extensions
Requires-Dist: torch (>=1.1.0)
Requires-Dist: opencv-python (>=3.4.19)
Requires-Dist: loguru (>=0.7.0)
